pysaver.py
pysaver-0.0.7.dist-info/LICENSE.txt
pysaver-0.0.7.dist-info/METADATA
pysaver-0.0.7.dist-info/WHEEL
pysaver-0.0.7.dist-info/top_level.txt
pysaver-0.0.7.dist-info/RECORD
