Metadata-Version: 2.1
Name: pysaver
Version: 0.0.7
Home-page: https://github.com/mjlally/pysaver
Author: M J Lally
Author-email: m.j.lally@outlook.com
License: MIT
Keywords: pysaver
License-File: LICENSE.txt
